Metadata-Version: 2.1
Name: boto3-stubs-reducer
Version: 0.1.0
Summary: Reduce invalid modules from boto3-stubs stub files
Home-page: https://github.com/smatsumt/boto3-stubs-reducer
Author: Shinji Matsumoto
Author-email: shinji.mtsmt@gmail.com
License: MIT
Platform: UNKNOWN
